geoph/__init__.py
geoph/geoph_impl.cpython-39-x86_64-linux-gnu.so
geoph.libs/libgmp-d944b113.so.10.3.2
geoph.libs/libgmpxx-8b3a383a.so.4.5.2
geoph.libs/libgomp-e985bcbb.so.1.0.0
geoph.libs/libmpfr-b7fafdf8.so.4.1.6
geoph.libs/libtbb-f09e8534.so.2
geoph.libs/libtbbmalloc-11090abd.so.2
geoph-0.0.1.dist-info/METADATA
geoph-0.0.1.dist-info/WHEEL
geoph-0.0.1.dist-info/RECORD
