Metadata-Version: 2.1
Name: geoph
Version: 0.0.1
Summary: A Delaunay-Rips persistent homology library
Project-URL: Homepage, https://github.com/MClemot/GeoPH
Requires-Python: >=3.9
